sws_spark_dissemination_helper/SWSBronzeIcebergSparkHelper.py
sws_spark_dissemination_helper/SWSDatatablesExportHelper.py
sws_spark_dissemination_helper/SWSEasyIcebergSparkHelper.py
sws_spark_dissemination_helper/SWSGoldIcebergSparkHelper.py
sws_spark_dissemination_helper/SWSPostgresSparkReader.py
sws_spark_dissemination_helper/SWSSilverIcebergSparkHelper.py
sws_spark_dissemination_helper/__init__.py
sws_spark_dissemination_helper/constants.py
sws_spark_dissemination_helper/utils.py
sws_spark_dissemination_helper-0.0.193.dist-info/METADATA
sws_spark_dissemination_helper-0.0.193.dist-info/WHEEL
sws_spark_dissemination_helper-0.0.193.dist-info/licenses/LICENSE
sws_spark_dissemination_helper-0.0.193.dist-info/RECORD
