Metadata-Version: 2.4
Name: sws-spark-dissemination-helper
Version: 0.0.193
Summary: A Python helper package providing streamlined Spark functions for efficient data dissemination processes
Project-URL: Repository, https://github.com/un-fao/fao-sws-it-python-spark-dissemination-helper
Author-email: Daniele Mansillo <danielemansillo@gmail.com>
License: MIT License
License-File: LICENSE
Classifier: License :: OSI Approved :: MIT License
Classifier: Operating System :: OS Independent
Classifier: Programming Language :: Python :: 3
Requires-Python: >=3.9
Requires-Dist: annotated-types==0.7.0
Requires-Dist: boto3>=1.40.0
Requires-Dist: botocore>=1.40.0
Requires-Dist: certifi==2025.1.31
Requires-Dist: charset-normalizer==3.4.1
Requires-Dist: idna>=3.10
Requires-Dist: jmespath==1.0.1
Requires-Dist: numpy==2.0.2
Requires-Dist: pandas==2.3.3
Requires-Dist: py4j==0.10.9.7
Requires-Dist: pydantic-core==2.27.2
Requires-Dist: pydantic==2.10.6
Requires-Dist: pyspark==3.5.4
Requires-Dist: python-dateutil==2.9.0.post0
Requires-Dist: python-dotenv==0.19.2
Requires-Dist: pytz==2025.2
Requires-Dist: requests==2.32.3
Requires-Dist: s3transfer>=0.11.2
Requires-Dist: six==1.17.0
Requires-Dist: sws-api-client==2.7.3
Requires-Dist: typing-extensions>=4.12.2
Requires-Dist: tzdata==2025.2
Requires-Dist: urllib3==1.26.20
